<?xml version="1.0" encoding="utf-8"?>
<!--
  ~ Copyright (C) 2017 Citrus-CAF Project
  ~ Licensed under the Apache License, Version 2.0 (the "License");
  ~ you may not use this file except in compliance with the License.
  ~ You may obtain a copy of the License at
  ~
  ~      http://www.apache.org/licenses/LICENSE-2.0
  ~
  ~ Unless required by applicable law or agreed to in writing, software
  ~ distributed under the License is distributed on an "AS IS" BASIS,
  ~ WITHOUT WARRANTIES OR CONDITIONS OF ANY KIND, either express or implied.
  ~ See the License for the specific language governing permissions and
  ~ limitations under the License.
  ~
  -->

<resources>

    <!-- Colors for the notification actions -->
    <color name="notification_action_accept">@*android:color/holo_blue_bright</color>
    <color name="notification_action_answer_video">@*android:color/holo_blue_bright</color>
    <color name="notification_action_dismiss">@*android:color/holo_blue_bright</color>
    <color name="notification_action_end_call">@*android:color/holo_blue_bright</color>

    <!-- Main theme colors -->
    <color name="dialer_theme_color_20pct">@*android:color/ripple_material_dark</color>
    <color name="dialer_snackbar_action_text_color">@*android:color/holo_blue_bright</color>
    <color name="dialtacts_theme_color">@*android:color/holo_blue_bright</color>

    <!-- Color of ripples used for views with dark backgrounds -->
    <color name="dialer_ripple_material_dark">@*android:color/ripple_material_dark</color>

    <!-- Color of ripples used for views with light backgrounds -->
    <color name="dialer_ripple_material_light">@*android:color/ripple_material_light</color>

    <!--Tabs ripple -->
    <color name="tab_ripple_color">@*android:color/ripple_material_dark</color>
    <color name="tab_accent_color">@*android:color/holo_blue_bright</color>

    <!-- Primary text color in the Phone app -->
    <color name="dialer_primary_text_color">@*android:color/text_color_primary</color>
    <color name="dialer_secondary_color">@*android:color/holo_blue_bright</color>
    <color name="dialer_secondary_text_color">@*android:color/text_color_secondary</color>
    <color name="dialer_edit_text_hint_color">@*android:color/text_color_secondary</color>

    <!-- White background for dialer -->
    <color name="blue_grey_100">@*android:color/holo_blue_bright</color>

    <!-- Dialpad -->
    <color name="dialpad_fab_green">@*android:color/holo_blue_bright</color>
    <color name="dialpad_digits_text_color">@*android:color/text_color_primary</color>
    <color name="dialpad_icon_tint">@*android:color/holo_blue_bright</color>
    <color name="dialpad_secondary_text_color">@*android:color/holo_blue_bright</color>
    <color name="dialpad_separator_line_color">@*android:color/holo_blue_bright</color>
    <color name="dialpad_voicemail_tint">@*android:color/holo_blue_bright</color>
    <color name="dialpad_primary_text_color">@*android:color/text_color_primary</color>

    <!-- Color of call type icons in call log, e.g. voicemail, video, WiFi, HD etc. -->
    <color name="call_type_icon_color">@*android:color/holo_blue_bright</color>

    <!-- Call log -->
    <color name="call_log_icon_tint">@*android:color/holo_blue_bright</color>
    <color name="call_log_primary_color">@*android:color/text_color_primary</color>
    <color name="call_log_detail_color">@*android:color/text_color_secondary</color>
    <color name="call_log_day_group_heading_color">@*android:color/holo_blue_bright</color>
    <color name="call_log_action_divider">@*android:color/holo_blue_bright</color>
    <color name="call_log_action_text">@*android:color/text_color_primary</color>
    <color name="call_log_action_color">@*android:color/text_color_primary</color>

    <!-- Text color for section header. -->
    <color name="section_header_text_color">#ffffffff</color>

    <!-- Settings -->
    <color name="setting_button_color">@*android:color/holo_blue_bright</color>

    <!-- Searchbox -->
    <color name="searchbox_hint_text_color">@*android:color/text_color_primary</color>
    <color name="searchbox_icon_tint">@*android:color/holo_blue_bright</color>
    <color name="searchbox_text_color">@*android:color/text_color_primary</color>

    <color name="tab_selected_underline_color">@*android:color/holo_blue_bright</color>

    <color name="dialer_flat_button_text_color">@*android:color/holo_blue_bright</color>

    <!-- IncallUI -->
    <color name="incoming_answer_icon">@android:color/transparent</color>
    <color name="incall_background_gradient_top">@*android:color/background_holo_dark</color>
    <color name="incall_background_gradient_middle">@*android:color/background_holo_dark</color>
    <color name="incall_background_gradient_bottom">@*android:color/background_holo_dark</color>
    <color name="incall_background_multiwindow">@*android:color/background_holo_dark</color>
    <color name="incall_background_gradient_spam_top">@*android:color/background_holo_dark</color>
    <color name="incall_background_gradient_spam_middle">@*android:color/background_holo_dark</color>
    <color name="incall_background_gradient_spam_bottom">@*android:color/background_holo_dark</color>
    <color name="incall_background_multiwindow_spam">@*android:color/background_holo_dark</color>
</resources>
