<?xml version="1.0" encoding="utf-8"?>
<!-- Copyright (C) 2007 The Android Open Source Project

     Licensed under the Apache License, Version 2.0 (the "License");
     you may not use this file except in compliance with the License.
     You may obtain a copy of the License at

          http://www.apache.org/licenses/LICENSE-2.0

     Unless required by applicable law or agreed to in writing, software
     distributed under the License is distributed on an "AS IS" BASIS,
     WITHOUT WARRANTIES OR CONDITIONS OF ANY KIND, either express or implied.
     See the License for the specific language governing permissions and
     limitations under the License.
-->


<resources>
    <drawable name="grayBg">@*android:color/background_dark</drawable>

    <style name="SettingsLight" parent="@*android:style/Theme.Material">
        <item name="android:windowBackground">@*com.android.phone:color/phone_settings_background_color</item>
        <item name="android:windowContentOverlay">@null</item>
        <item name="android:actionBarStyle">@*com.android.phone:style/DialtactsActionBarStyle</item>
        <item name="android:actionMenuTextColor">@*com.android.phone:color/phone_settings_actionbar_text_color</item>
        <item name="android:actionOverflowButtonStyle">@*com.android.phone:style/DialtactsActionBarOverflow</item>
        <item name="android:homeAsUpIndicator">@*com.android.phone:drawable/ic_back_arrow</item>
        <item name="android:windowActionBarOverlay">false</item>
        <item name="android:colorPrimaryDark">@*com.android.phone:color/actionbar_background_color_dark</item>
        <!-- Setting text. -->
        <item name="android:textColorPrimary">@*com.android.phone:color/settings_text_color_primary</item>
        <!-- Setting description. -->
        <item name="android:textColorSecondary">@*com.android.phone:color/settings_text_color_secondary</item>
        <item name="android:navigationBarColor">@*android:color/holo_blue_light</item>
    </style>


    <style name="NetworkOperatorsSettingsTheme" parent="@android:style/Theme.DeviceDefault.Settings">
        <item name="android:switchPreferenceStyle">@*com.android.phone:style/SettingsSwitchPreference</item>
        <item name="android:preferenceCategoryStyle">@*com.android.phone:style/SettingsPreferenceCategory</item>
        <item name="android:preferenceStyle">@*com.android.phone:style/SettingsPreference</item>
        <item name="android:dialogPreferenceStyle">@*com.android.phone:style/SettingsDialogPreference</item>
        <item name="android:preferenceScreenStyle">@*com.android.phone:style/SettingsPreferenceScreen</item>
    </style>

    <style name="EmergencyDialerTheme" parent="@*android:style/Theme.DeviceDefault.Settings.Dark.NoActionBar">
        <item name="android:colorPrimaryDark">@*android:color/holo_blue_dark</item>
        <item name="android:colorBackgroundCacheHint">@null</item>
        <item name="android:windowShowWallpaper">true</item>
        <item name="android:statusBarColor">@android:color/transparent</item>
        <item name="android:navigationBarColor">@android:color/transparent</item>
        <item name="android:homeAsUpIndicator">@*com.android.phone:drawable/ic_back_arrow</item>
        <item name="*com.android.phone:emergencyButtonBackgroundColor">@*android:color/holo_blue_dark</item>
        <item name="*com.android.phone:dialpadTheme">@*com.android.phone:style/Dialpad_DarkTransparent</item>
    </style>

    <style name="EmergencyDialerThemeDark" parent="@*com.android.phone:style/EmergencyDialerTheme">
        <item name="android:textColor">?android:attr/textColorPrimaryInverse</item>
        <item name="*com.android.phone:emergencyButtonBackgroundColor">@*android:color/holo_blue_dark</item>
        <item name="*com.android.phone:dialpadTheme">@*com.android.phone:style/Dialpad_LightTransparent</item>
    </style>

    <style name="SimImportTheme" parent="@android:style/Theme.Material">
        <item name="android:actionBarStyle">@*com.android.phone:style/TelephonyActionBarStyle</item>
        <item name="android:colorPrimaryDark">@*android:color/holo_blue_dark</item>
        <item name="android:homeAsUpIndicator">@*com.android.phone:drawable/ic_back_arrow</item>
        <item name="android:actionOverflowButtonStyle">@*com.android.phone:style/DialtactsActionBarOverflow</item>
        <item name="android:navigationBarColor">@*android:color/holo_blue_light</item>
    </style>

    <style name="OutgoingCallBroadcasterTheme" parent="@android:style/Theme.Material.NoActionBar">
        <item name="android:windowBackground">@android:color/background_dark</item>
        <item name="*android:windowAnimationStyle">@*com.android.phone:style/OutgoingAnimationStyle</item>
    </style>


</resources>
